public_transport_datasets/__init__.py
public_transport_datasets/dataset.py
public_transport_datasets/datasets_provider.py
public_transport_datasets/gtfs_vehicles.py
public_transport_datasets/rate_limited_session.py
public_transport_datasets/siri_vehicles.py
public_transport_datasets/tfl_vehicles.py
public_transport_datasets/vehicles.py
public_transport_datasets/providers/GTFS/AU_Adelaide_Metro_bus.json
public_transport_datasets/providers/GTFS/AU_Canberra_Metro_Opera_bus.json
public_transport_datasets/providers/GTFS/AU_TransLink_South_East_bus.json
public_transport_datasets/providers/GTFS/AU_TransLink_Sunbus_Cai_bus.json
public_transport_datasets/providers/GTFS/AU_Translink_bus_3.json
public_transport_datasets/providers/GTFS/CA_Barrie_Transit_bus.json
public_transport_datasets/providers/GTFS/CA_Bus_Mont-Tremblant_bus.json
public_transport_datasets/providers/GTFS/CA_Calgary_Transit_bus.json
public_transport_datasets/providers/GTFS/CA_Durham_Region_Transi_bus.json
public_transport_datasets/providers/GTFS/CA_Edmonton_Transit_Sys_bus.json
public_transport_datasets/providers/GTFS/CA_Halifax_Transit_bus.json
public_transport_datasets/providers/GTFS/CA_Kingston_Transit_bus.json
public_transport_datasets/providers/GTFS/CA_L_Inter_des_Laurenti_bus.json
public_transport_datasets/providers/GTFS/CA_London_Transit_Commi_bus.json
public_transport_datasets/providers/GTFS/CA_MRC_de_Montcalm_bus.json
public_transport_datasets/providers/GTFS/CA_MiWay_bus.json
public_transport_datasets/providers/GTFS/CA_Port_Alberni_bus.json
public_transport_datasets/providers/GTFS/CA_Saint_Jean_Sur_Riche_bus.json
public_transport_datasets/providers/GTFS/CA_Soci_t__de_Transport_bus_1.json
public_transport_datasets/providers/GTFS/CA_Soci_t__de_transport_bus.json
public_transport_datasets/providers/GTFS/CA_Thunder_Bay_Transit_bus.json
public_transport_datasets/providers/GTFS/CA_TransLink_Vancouver_bus.json
public_transport_datasets/providers/GTFS/CA_York_Region_Transit_bus.json
public_transport_datasets-0.1.62.dist-info/licenses/LICENSE
public_transport_datasets-0.1.62.dist-info/METADATA
public_transport_datasets-0.1.62.dist-info/WHEEL
public_transport_datasets-0.1.62.dist-info/top_level.txt
public_transport_datasets-0.1.62.dist-info/RECORD
