Metadata-Version: 2.4
Name: public_transport_datasets
Version: 0.1.62
Summary: A Python package for public transport datasets for multiple cities.
Home-page: https://github.com/maxmazzeschi/public-transport-datasets
Author: Max Mazzeschi
Author-email: max.mazzeschi@gmail.com
License: Apache-2.0
Classifier: Programming Language :: Python :: 3
Classifier: License :: OSI Approved :: Apache Software License
Classifier: Operating System :: OS Independent
License-File: LICENSE
Requires-Dist: requests
Requires-Dist: gtfs-realtime-bindings
Requires-Dist: jsonpath-ng
Requires-Dist: duckdb
Requires-Dist: geopandas
Requires-Dist: shapely
Dynamic: author
Dynamic: author-email
Dynamic: classifier
Dynamic: description
Dynamic: description-content-type
Dynamic: home-page
Dynamic: license
Dynamic: license-file
Dynamic: requires-dist
Dynamic: summary
